cinetone/__init__.py
cinetone-0.0.3.dist-info/LICENSE
cinetone-0.0.3.dist-info/METADATA
cinetone-0.0.3.dist-info/WHEEL
cinetone-0.0.3.dist-info/entry_points.txt
cinetone-0.0.3.dist-info/top_level.txt
cinetone-0.0.3.dist-info/RECORD
